odoo10_addon_base_sms_client-10.0.1.0.0-py2.7-nspkg.pth
odoo/addons/base_sms_client/README.rst
odoo/addons/base_sms_client/__init__.py
odoo/addons/base_sms_client/__manifest__.py
odoo/addons/base_sms_client/data/sms_gateway_data.xml
odoo/addons/base_sms_client/i18n/ar.po
odoo/addons/base_sms_client/i18n/ca.po
odoo/addons/base_sms_client/i18n/de.po
odoo/addons/base_sms_client/i18n/es.po
odoo/addons/base_sms_client/i18n/fr.po
odoo/addons/base_sms_client/i18n/pt_BR.po
odoo/addons/base_sms_client/images/client.jpeg
odoo/addons/base_sms_client/images/gateway.jpeg
odoo/addons/base_sms_client/images/gateway_access.jpeg
odoo/addons/base_sms_client/images/send_sms.jpeg
odoo/addons/base_sms_client/images/sms.jpeg
odoo/addons/base_sms_client/models/__init__.py
odoo/addons/base_sms_client/models/server_action.py
odoo/addons/base_sms_client/models/sms_gateway.py
odoo/addons/base_sms_client/models/sms_sms.py
odoo/addons/base_sms_client/models/sms_template.py
odoo/addons/base_sms_client/security/groups.xml
odoo/addons/base_sms_client/security/ir.model.access.csv
odoo/addons/base_sms_client/security/ir.rule.csv
odoo/addons/base_sms_client/static/src/img/icon.png
odoo/addons/base_sms_client/views/server_action_view.xml
odoo/addons/base_sms_client/views/sms_gateway_view.xml
odoo/addons/base_sms_client/views/smstemplate_view.xml
odoo/addons/base_sms_client/wizard/__init__.py
odoo/addons/base_sms_client/wizard/mass_sms.py
odoo/addons/base_sms_client/wizard/mass_sms_view.xml
odoo10_addon_base_sms_client-10.0.1.0.0.dist-info/DESCRIPTION.rst
odoo10_addon_base_sms_client-10.0.1.0.0.dist-info/METADATA
odoo10_addon_base_sms_client-10.0.1.0.0.dist-info/RECORD
odoo10_addon_base_sms_client-10.0.1.0.0.dist-info/WHEEL
odoo10_addon_base_sms_client-10.0.1.0.0.dist-info/metadata.json
odoo10_addon_base_sms_client-10.0.1.0.0.dist-info/namespace_packages.txt
odoo10_addon_base_sms_client-10.0.1.0.0.dist-info/top_level.txt
