Metadata-Version: 2.0
Name: odoo10-addon-base-sms-client
Version: 10.0.1.0.0
Summary: Sending SMSs very easily, individually or collectively.
Home-page: http://julius.fr
Author: Julius Network Solutions,SYLEAM,Odoo Community Association (OCA),Akretion
Author-email: support@odoo-community.org
License: AGPL-3
Platform: UNKNOWN
Classifier: Programming Language :: Python :: 2.7
Classifier: Framework :: Odoo
Classifier: License :: OSI Approved :: GNU Affero General Public License v3
Requires-Dist: odoo (<10.1dev,>=10.0)
Requires-Dist: odoo10-addon-base-phone
Requires-Dist: odoo10-addon-keychain
